symclosestwannier/__init__.py
symclosestwannier/analyzer/analyzer.py
symclosestwannier/analyzer/band.py
symclosestwannier/analyzer/get_band.py
symclosestwannier/analyzer/get_response.py
symclosestwannier/analyzer/response.py
symclosestwannier/cw/amn.py
symclosestwannier/cw/cw_creator.py
symclosestwannier/cw/cw_info.py
symclosestwannier/cw/cw_manager.py
symclosestwannier/cw/cw_model.py
symclosestwannier/cw/cwin.py
symclosestwannier/cw/eig.py
symclosestwannier/cw/mmn.py
symclosestwannier/cw/nnkp.py
symclosestwannier/cw/spn.py
symclosestwannier/cw/uHu.py
symclosestwannier/cw/umat.py
symclosestwannier/cw/win.py
symclosestwannier/scripts/postcw.py
symclosestwannier/scripts/pw2cw.py
symclosestwannier/util/band.py
symclosestwannier/util/cohp.py
symclosestwannier/util/constants.py
symclosestwannier/util/dos.py
symclosestwannier/util/fermi_surface.py
symclosestwannier/util/get_oper_R.py
symclosestwannier/util/header.py
symclosestwannier/util/hr_utility.py
symclosestwannier/util/lindhard.py
symclosestwannier/util/message.py
symclosestwannier/util/spread.py
symclosestwannier/util/tb_slater_koster.py
symclosestwannier/util/utility.py
symclosestwannier-2.0.4.dist-info/LICENSE
symclosestwannier-2.0.4.dist-info/METADATA
symclosestwannier-2.0.4.dist-info/WHEEL
symclosestwannier-2.0.4.dist-info/entry_points.txt
symclosestwannier-2.0.4.dist-info/top_level.txt
symclosestwannier-2.0.4.dist-info/RECORD
