Metadata-Version: 2.2
Name: symclosestwannier
Version: 2.0.4
Summary: A Python library for Symmetry-Adapted Closest Wannier (SymCW) Tight-Binding model based on Plane-Wave DFT calculation.
Author-email: Rikuto Oiwa <ro.qp.07@gmail.com>
Project-URL: Homepage, https://github.com/CMT-MU/SymClosestWannier
Project-URL: Issues, https://github.com/CMT-MU/SymClosestWannier/issues
Keywords: dft,wannier function,tight-binding model,symmetry,materials science
Classifier: Intended Audience :: Science/Research
Classifier: Topic :: Scientific/Engineering :: Information Analysis
Classifier: License :: OSI Approved :: GNU General Public License v3 or later (GPLv3+)
Classifier: Operating System :: Microsoft :: Windows
Classifier: Operating System :: POSIX
Classifier: Operating System :: MacOS
Classifier: Programming Language :: Python :: 3.11
Classifier: Programming Language :: Python :: 3.12
Classifier: Programming Language :: Python :: 3.13
Requires-Python: >=3.9
License-File: LICENSE
Requires-Dist: gcoreutils
Requires-Dist: multipie
Requires-Dist: xmltodict
Requires-Dist: fortio
Requires-Dist: h5py
Requires-Dist: tqdm
Provides-Extra: dev
Requires-Dist: jupyter-book; extra == "dev"
Requires-Dist: ghp-import; extra == "dev"
Requires-Dist: multipie; extra == "dev"
Requires-Dist: qtdraw; extra == "dev"
